{
  "project_info": {
    "project_number": "1072908047823",
    "firebase_url": "https://ivoohcliente.firebaseio.com",
    "project_id": "ivoohcliente",
    "storage_bucket": "ivoohcliente.appspot.com"
  },
  "client": [
    {
      "client_info": {
        "mobilesdk_app_id": "1:1072908047823:android:2c3546deb3775066",
        "android_client_info": {
          "package_name": "com.fvf.ivoohcliente"
        }
      },
      "oauth_client": [
        {
          "client_id": "1072908047823-908iungtq2dv6lb6q8nit3vd5ddne9ro.apps.googleusercontent.com",
          "client_type": 1,
          "android_info": {
            "package_name": "com.fvf.ivoohcliente",
            "certificate_hash": "eeb0c338fe7112f1b3e7741905dd95b0b382dabd"
          }
        },
        {
          "client_id": "1072908047823-omp29g253e3v8p7ch921nnuckpn8898k.apps.googleusercontent.com",
          "client_type": 3
        }
      ],
      "api_key": [
        {
          "current_key": "AIzaSyAtSP7lTEcLiIHQARwIRXnqc774jOk2J2c"
        }
      ],
      "services": {
        "appinvite_service": {
          "other_platform_oauth_client": [
            {
              "client_id": "1072908047823-omp29g253e3v8p7ch921nnuckpn8898k.apps.googleusercontent.com",
              "client_type": 3
            }
          ]
        }
      }
    }
  ],
  "configuration_version": "1"
}